datauri/__init__.py
datauri/exceptions.py
datauri/py.typed
python_datauri-3.0.1.dist-info/LICENSE
python_datauri-3.0.1.dist-info/METADATA
python_datauri-3.0.1.dist-info/WHEEL
python_datauri-3.0.1.dist-info/top_level.txt
python_datauri-3.0.1.dist-info/RECORD
