Metadata-Version: 2.1
Name: python-datauri
Version: 3.0.1
Summary: A li'l class for data URI manipulation in Python
Home-page: https://github.com/fcurella/python-datauri/
Maintainer: Flavio Curella
Maintainer-email: flavio.curella@gmail.com
License: Unlicense
Platform: any
Classifier: Development Status :: 4 - Beta
Classifier: License :: OSI Approved :: The Unlicense (Unlicense)
Classifier: Operating System :: OS Independent
Classifier: Programming Language :: Python
Classifier: Programming Language :: Python :: 3
Classifier: Programming Language :: Python :: 3.8
Classifier: Programming Language :: Python :: 3.9
Classifier: Programming Language :: Python :: 3.10
License-File: LICENSE
Requires-Dist: cached-property
Requires-Dist: typing_extensions
